echo/__init__.py
echo/callback_container.py
echo/conftest.py
echo/containers.py
echo/core.py
echo/selection.py
echo/version.py
echo/qt/__init__.py
echo/qt/autoconnect.py
echo/qt/connect.py
echo/qt/tests/__init__.py
echo/qt/tests/helpers.py
echo/qt/tests/test_autoconnect.py
echo/qt/tests/test_connect.py
echo/qt/tests/test_connect_combo_selection.py
echo/qt/tests/test_connect_list_selection.py
echo/tests/__init__.py
echo/tests/test_callback_container.py
echo/tests/test_containers.py
echo/tests/test_core.py
echo/tests/test_selection.py
echo-0.11.0.dist-info/licenses/LICENSE
echo-0.11.0.dist-info/METADATA
echo-0.11.0.dist-info/WHEEL
echo-0.11.0.dist-info/top_level.txt
echo-0.11.0.dist-info/zip-safe
echo-0.11.0.dist-info/RECORD
