Metadata-Version: 2.4
Name: echo
Version: 0.11.0
Summary: Callback Properties in Python
Author-email: Chris Beaumont and Thomas Robitaille <thomas.robitaille@gmail.com>
Maintainer-email: Chris Beaumont and Thomas Robitaille <thomas.robitaille@gmail.com>
License-Expression: MIT
Project-URL: homepage, https://github.com/glue-viz/echo
Classifier: Intended Audience :: Developers
Classifier: Natural Language :: English
Classifier: Operating System :: OS Independent
Classifier: Programming Language :: Python :: 3 :: Only
Classifier: Programming Language :: Python :: 3.10
Classifier: Programming Language :: Python :: 3.11
Classifier: Programming Language :: Python :: 3.12
Classifier: Programming Language :: Python :: 3.13
Requires-Python: >=3.10
License-File: LICENSE
Requires-Dist: numpy
Provides-Extra: docs
Requires-Dist: numpydoc; extra == "docs"
Requires-Dist: sphinx; extra == "docs"
Requires-Dist: sphinx-automodapi; extra == "docs"
Requires-Dist: sphinx-rtd-theme; extra == "docs"
Provides-Extra: qt
Requires-Dist: pyqt5>=5.14; extra == "qt"
Requires-Dist: qtpy; extra == "qt"
Provides-Extra: test
Requires-Dist: pytest; extra == "test"
Requires-Dist: pytest-cov; extra == "test"
Dynamic: license-file
